{
  "appPageId" : "7945fd4d-d5d2-403e-bc9f-6f3a42c99835",
  "componentName" : "siteforce:sldsOneColLayout",
  "dataProviders" : [ ],
  "id" : "83d15bdf-6695-4a7e-88f4-8f1d600c6315",
  "label" : "Messages",
  "regions" : [ {
    "components" : [ {
      "componentAttributes" : { },
      "componentName" : "forceChatter:messages",
      "id" : "164bffa5-5a7b-4479-b48b-e0fc75219db0",
      "renderPriority" : "NEUTRAL",
      "renditionMap" : { },
      "type" : "component"
    } ],
    "id" : "f88b482d-f66d-4c34-ad70-4e4ac22c92e7",
    "regionName" : "content",
    "type" : "region"
  } ],
  "themeLayoutType" : "Inner",
  "type" : "view",
  "viewType" : "messages"
}